boson/__init__.py
boson/configure.py
boson/console.py
boson/boson_script/__init__.py
boson/boson_script/boson_script_analyzer.py
boson/boson_script/boson_script_parser.py
boson/boson_script/command.py
boson/code_generator/__init__.py
boson/code_generator/generator.py
boson/code_generator/templates/c++.template
boson/code_generator/templates/python3.template
boson/code_generator/templates/lexer/c++.template
boson/code_generator/templates/lexer/python3.template
boson/code_generator/templates/parser/c++.template
boson/code_generator/templates/parser/python3.template
boson/lexer_generator/__init__.py
boson/lexer_generator/generator.py
boson/lexer_generator/lexical_dfa.py
boson/lexer_generator/lexical_nfa.py
boson/lexer_generator/regular_analyzer.py
boson/lexer_generator/regular_parser.py
boson/parser_generator/__init__.py
boson/parser_generator/generator.py
boson/parser_generator/bottom_up_generator/__init__.py
boson/parser_generator/bottom_up_generator/canonical_generator.py
boson/parser_generator/bottom_up_generator/generator.py
boson/parser_generator/bottom_up_generator/lalr_generator.py
boson/parser_generator/bottom_up_generator/lr_generator.py
boson/parser_generator/bottom_up_generator/slr_generator.py
boson-1.4.dist-info/METADATA
boson-1.4.dist-info/RECORD
boson-1.4.dist-info/WHEEL
boson-1.4.dist-info/entry_points.txt
boson-1.4.dist-info/top_level.txt
